trinocli/__init__.py
trinocli/trinocli.py
trinocli/bin/trino-cli.jar
pytrinocli-446.0.16.dist-info/METADATA
pytrinocli-446.0.16.dist-info/WHEEL
pytrinocli-446.0.16.dist-info/entry_points.txt
pytrinocli-446.0.16.dist-info/top_level.txt
pytrinocli-446.0.16.dist-info/RECORD
