Metadata-Version: 2.4
Name: pytrinocli
Version: 446.0.16
Summary: Trino CLI
Author-email: Klim Naidenov <pymirror@mail.ru>
Project-URL: Homepage, https://git@git.sourcecraft.dev/pymirror/pytrinocli.git
Project-URL: Issues, https://sourcecraft.dev/pymirror/pytrinocli/issues
Classifier: Operating System :: OS Independent
Requires-Python: >=3.0
